erbsland/conf/__init__.py
erbsland/conf/_version.py
erbsland/conf/access_check.py
erbsland/conf/datetime.py
erbsland/conf/document.py
erbsland/conf/error.py
erbsland/conf/file_access_check.py
erbsland/conf/file_source_resolver.py
erbsland/conf/location.py
erbsland/conf/name.py
erbsland/conf/name_path.py
erbsland/conf/parser.py
erbsland/conf/signature.py
erbsland/conf/signer.py
erbsland/conf/source.py
erbsland/conf/source_resolver.py
erbsland/conf/test_output.py
erbsland/conf/time_delta.py
erbsland/conf/value.py
erbsland/conf/value_type.py
erbsland/conf/impl/__init__.py
erbsland/conf/impl/assignment.py
erbsland/conf/impl/document_impl.py
erbsland/conf/impl/features.py
erbsland/conf/impl/file_source.py
erbsland/conf/impl/limits.py
erbsland/conf/impl/name_path_lexer.py
erbsland/conf/impl/parser_impl.py
erbsland/conf/impl/parser_settings.py
erbsland/conf/impl/position_counter.py
erbsland/conf/impl/sentinels.py
erbsland/conf/impl/stream_source.py
erbsland/conf/impl/text_escape.py
erbsland/conf/impl/text_source.py
erbsland/conf/impl/token.py
erbsland/conf/impl/token_type.py
erbsland/conf/impl/value_impl.py
erbsland/conf/impl/value_storage_type.py
erbsland/conf/impl/value_tree_helper.py
erbsland/conf/impl/lexing/__init__.py
erbsland/conf/impl/lexing/assignment.py
erbsland/conf/impl/lexing/bool_value.py
erbsland/conf/impl/lexing/byte_value.py
erbsland/conf/impl/lexing/common_value.py
erbsland/conf/impl/lexing/cursor.py
erbsland/conf/impl/lexing/datetime_value.py
erbsland/conf/impl/lexing/float_value.py
erbsland/conf/impl/lexing/integer_value.py
erbsland/conf/impl/lexing/lexer.py
erbsland/conf/impl/lexing/name.py
erbsland/conf/impl/lexing/rule.py
erbsland/conf/impl/lexing/section.py
erbsland/conf/impl/lexing/spacing.py
erbsland/conf/impl/lexing/text.py
erbsland/conf/impl/lexing/types.py
erbsland/conf/impl/lexing/value.py
erbsland/conf/syntax/__init__.py
erbsland/conf/syntax/lexer.py
erbsland_conf-1.0.6.dist-info/METADATA
erbsland_conf-1.0.6.dist-info/WHEEL
erbsland_conf-1.0.6.dist-info/licenses/LICENSE
erbsland_conf-1.0.6.dist-info/RECORD
