Metadata-Version: 2.4
Name: erbsland-conf
Version: 1.0.6
Summary: A native Python parser for the Erbsland Configuration Language (ELCL)
Project-URL: Homepage, https://github.com/erbsland-dev/erbsland-py-conf
Project-URL: Issues, https://github.com/erbsland-dev/erbsland-py-conf/issues
Author-email: Tobias Erbsland / Erbsland DEV <info@erbsland.dev>
License:                                  Apache License
License-File: LICENSE
Requires-Python: >=3.12
